MergePythonSDK/__init__.py
MergePythonSDK/accounting/__init__.py
MergePythonSDK/accounting/api/__init__.py
MergePythonSDK/accounting/api/account_details_api.py
MergePythonSDK/accounting/api/account_token_api.py
MergePythonSDK/accounting/api/accounts_api.py
MergePythonSDK/accounting/api/addresses_api.py
MergePythonSDK/accounting/api/attachments_api.py
MergePythonSDK/accounting/api/available_actions_api.py
MergePythonSDK/accounting/api/balance_sheets_api.py
MergePythonSDK/accounting/api/cash_flow_statements_api.py
MergePythonSDK/accounting/api/company_info_api.py
MergePythonSDK/accounting/api/contacts_api.py
MergePythonSDK/accounting/api/credit_notes_api.py
MergePythonSDK/accounting/api/delete_account_api.py
MergePythonSDK/accounting/api/expenses_api.py
MergePythonSDK/accounting/api/force_resync_api.py
MergePythonSDK/accounting/api/generate_key_api.py
MergePythonSDK/accounting/api/income_statements_api.py
MergePythonSDK/accounting/api/invoices_api.py
MergePythonSDK/accounting/api/issues_api.py
MergePythonSDK/accounting/api/items_api.py
MergePythonSDK/accounting/api/journal_entries_api.py
MergePythonSDK/accounting/api/link_token_api.py
MergePythonSDK/accounting/api/linked_accounts_api.py
MergePythonSDK/accounting/api/passthrough_api.py
MergePythonSDK/accounting/api/payments_api.py
MergePythonSDK/accounting/api/phone_numbers_api.py
MergePythonSDK/accounting/api/purchase_orders_api.py
MergePythonSDK/accounting/api/regenerate_key_api.py
MergePythonSDK/accounting/api/sync_status_api.py
MergePythonSDK/accounting/api/tax_rates_api.py
MergePythonSDK/accounting/api/tracking_categories_api.py
MergePythonSDK/accounting/api/transactions_api.py
MergePythonSDK/accounting/api/vendor_credits_api.py
MergePythonSDK/accounting/api/webhook_receivers_api.py
MergePythonSDK/accounting/model/__init__.py
MergePythonSDK/accounting/model/account.py
MergePythonSDK/accounting/model/account_details.py
MergePythonSDK/accounting/model/account_details_and_actions.py
MergePythonSDK.ticketing-2.2.2.dist-info/LICENSE.md
MergePythonSDK.ticketing-2.2.2.dist-info/METADATA
MergePythonSDK.ticketing-2.2.2.dist-info/WHEEL
MergePythonSDK.ticketing-2.2.2.dist-info/top_level.txt
MergePythonSDK.ticketing-2.2.2.dist-info/RECORD
